WoyongSixinshuiQingsongLicaiZhuanqianwan/README.md
WoyongSixinshuiQingsongLicaiZhuanqianwan/__init__.py
WoyongSixinshuiQingsongLicaiZhuanqianwan/__main__.py
WoyongSixinshuiQingsongLicaiZhuanqianwan/file.epub
WoyongSixinshuiQingsongLicaiZhuanqianwan/index.html
WoyongSixinshuiQingsongLicaiZhuanqianwan/css/__init__.py
WoyongSixinshuiQingsongLicaiZhuanqianwan/css/annotations.css
WoyongSixinshuiQingsongLicaiZhuanqianwan/css/main.css
WoyongSixinshuiQingsongLicaiZhuanqianwan/css/normalize.css
WoyongSixinshuiQingsongLicaiZhuanqianwan/css/popup.css
WoyongSixinshuiQingsongLicaiZhuanqianwan/font/__init__.py
WoyongSixinshuiQingsongLicaiZhuanqianwan/font/fontello.eot
WoyongSixinshuiQingsongLicaiZhuanqianwan/font/fontello.svg
WoyongSixinshuiQingsongLicaiZhuanqianwan/font/fontello.ttf
WoyongSixinshuiQingsongLicaiZhuanqianwan/font/fontello.woff
WoyongSixinshuiQingsongLicaiZhuanqianwan/img/__init__.py
WoyongSixinshuiQingsongLicaiZhuanqianwan/img/annotator-glyph-sprite.png
WoyongSixinshuiQingsongLicaiZhuanqianwan/img/annotator-icon-sprite.png
WoyongSixinshuiQingsongLicaiZhuanqianwan/img/apple-touch-icon.png
WoyongSixinshuiQingsongLicaiZhuanqianwan/img/cancelfullscreen.png
WoyongSixinshuiQingsongLicaiZhuanqianwan/img/close.png
WoyongSixinshuiQingsongLicaiZhuanqianwan/img/fullscreen.png
WoyongSixinshuiQingsongLicaiZhuanqianwan/img/loader.gif
WoyongSixinshuiQingsongLicaiZhuanqianwan/img/menu-icon.png
WoyongSixinshuiQingsongLicaiZhuanqianwan/img/save.png
WoyongSixinshuiQingsongLicaiZhuanqianwan/img/saved.png
WoyongSixinshuiQingsongLicaiZhuanqianwan/img/settings-s.png
WoyongSixinshuiQingsongLicaiZhuanqianwan/img/settings.png
WoyongSixinshuiQingsongLicaiZhuanqianwan/img/star.png
WoyongSixinshuiQingsongLicaiZhuanqianwan/js/__init__.py
WoyongSixinshuiQingsongLicaiZhuanqianwan/js/epub.js
WoyongSixinshuiQingsongLicaiZhuanqianwan/js/epub.min.js
WoyongSixinshuiQingsongLicaiZhuanqianwan/js/epub.min.map
WoyongSixinshuiQingsongLicaiZhuanqianwan/js/hooks.min.js
woyong_sixinshui_qingsong_licai_zhuanqianwan-2022.10.15.0.dist-info/METADATA
woyong_sixinshui_qingsong_licai_zhuanqianwan-2022.10.15.0.dist-info/WHEEL
woyong_sixinshui_qingsong_licai_zhuanqianwan-2022.10.15.0.dist-info/entry_points.txt
woyong_sixinshui_qingsong_licai_zhuanqianwan-2022.10.15.0.dist-info/top_level.txt
woyong_sixinshui_qingsong_licai_zhuanqianwan-2022.10.15.0.dist-info/RECORD
